{
  "schema_version": "1.0",
  "mask_type_id": "mf70_eyes_full",
  "source_image": "Plan/Instructions/Operations/Pulled_Back_Artifacts/canny_w69_rightedge_masked_v3_seed711570105_20260707T132203-0500/images/canny_w69_rightedge_masked_v3_seed711570105_00001_.png",
  "coordinate_space": "active_source_image_pixels_768x768",
  "eye_polygons": {
    "viewer_left_visible_eye_aperture": [
      [
        286,
        329
      ],
      [
        296,
        319
      ],
      [
        313,
        316
      ],
      [
        330,
        321
      ],
      [
        340,
        331
      ],
      [
        328,
        340
      ],
      [
        309,
        342
      ],
      [
        292,
        337
      ]
    ],
    "viewer_right_visible_eye_aperture": [
      [
        397,
        329
      ],
      [
        407,
        320
      ],
      [
        426,
        316
      ],
      [
        445,
        320
      ],
      [
        459,
        331
      ],
      [
        448,
        341
      ],
      [
        426,
        344
      ],
      [
        407,
        339
      ]
    ]
  },
  "protected_neighbors": {
    "viewer_left_hair_occlusion_boundary_note": "viewer-left eye mask is clipped inside the visible aperture and intentionally does not extend into the curl mass over the outer eye/temple.",
    "brows_and_eyelids_note": "eyes_full candidate excludes eyebrow strips and most eyelid skin; eyelids remain separate child/neighbor regions."
  },
  "candidate_only": true,
  "promotion_allowed": false
}
