{
    "schema_version":  "1.0",
    "evidence_id":  "W66-LOCAL-COMFYUI-RUN-PACKAGE-SMOKE-20260707T040239-0500",
    "timestamp":  "2026-07-07T04:02:39-05:00",
    "mode":  "execute",
    "project_root":  "C:\\Comfy_UI_Main",
    "local_only":  true,
    "aws_contacted":  false,
    "github_api_contacted":  false,
    "civitai_contacted":  false,
    "ec2_started":  false,
    "generation_executed":  true,
    "lane_id":  "sdxl_realvisxl_base_lane",
    "api_base_url":  "http://127.0.0.1:8188",
    "run_package":  {
                        "supplied":  true,
                        "file":  "runtime_artifacts/run_packages/realvisxl_hands_contact_robustness_w69_seed811006305/RUN_PACKAGE_MANIFEST.json",
                        "found":  true,
                        "valid":  true,
                        "errors":  [

                                   ],
                        "run_id":  "realvisxl_hands_contact_robustness_w69_seed811006305",
                        "lane_id":  "sdxl_realvisxl_base_lane",
                        "lane_match":  true,
                        "result":  "pass_local_only",
                        "prompt_request":  {
                                               "path":  "runtime_artifacts/run_packages/realvisxl_hands_contact_robustness_w69_seed811006305/prompt_request.json",
                                               "expected_sha256":  "dd0fab09e4d56654590e2d63136c92db1714b6898da858f4689858d59666e1ab",
                                               "actual_sha256":  "dd0fab09e4d56654590e2d63136c92db1714b6898da858f4689858d59666e1ab",
                                               "hash_match":  true,
                                               "json_valid":  true,
                                               "node_count":  7,
                                               "client_id":  "codex-realvisxl-hands-robustness-b"
                                           }
                    },
    "local_comfy":  {
                        "root":  "C:\\Comfy_UI_Main\\ComfyUI",
                        "python":  "C:\\Comfy_UI_Main\\ComfyUI\\.venv\\Scripts\\python.exe",
                        "extra_model_paths_config":  "config/comfyui_extra_model_paths.yaml",
                        "process_id":  84744,
                        "started_by_helper":  true,
                        "stopped_by_helper":  true,
                        "port_closed_after_stop":  true
                    },
    "object_info":  {
                        "status":  "pass",
                        "node_count":  791,
                        "required_nodes_present":  [
                                                       "CheckpointLoaderSimple",
                                                       "EmptyLatentImage",
                                                       "CLIPTextEncode",
                                                       "KSampler",
                                                       "VAEDecode",
                                                       "SaveImage"
                                                   ],
                        "missing_required_nodes":  [

                                                   ]
                    },
    "prompt_id":  "f8226a4a-37a7-4a0c-8c85-d8d34f42a566",
    "history_status":  "outputs_found",
    "output_images":  [
                          {
                              "node_id":  "9",
                              "filename":  "codex_realvisxl_hands_contact_robustness_b_00001_.png",
                              "subfolder":  "",
                              "type":  "output"
                          }
                      ],
    "pulled_artifacts":  [
                             {
                                 "source":  "ComfyUI/output/codex_realvisxl_hands_contact_robustness_b_00001_.png",
                                 "local_path":  "Plan/Instructions/Operations/Pulled_Back_Artifacts/realvisxl_hands_contact_robustness_seed811006305_20260707T040300-0500/images/codex_realvisxl_hands_contact_robustness_b_00001_.png",
                                 "bytes":  1349836,
                                 "sha256":  "382a87ad81d2375fdcf29146d2151ab4fcd49cf46c9f0d11f390dbf3adc37ba9",
                                 "node_id":  "9",
                                 "type":  "output"
                             }
                         ],
    "pullback_dir":  "Plan/Instructions/Operations/Pulled_Back_Artifacts/realvisxl_hands_contact_robustness_seed811006305_20260707T040300-0500",
    "result":  "pass_local_run_package_generation_smoke",
    "failure_category":  null,
    "errors":  [

               ],
    "next_action":  "Use local results for iteration only; EC2 target-runtime proof remains separate."
}