{
  "blocker_codes": [
    "DEPENDENCIES_RUNTIME_BENCHMARK_ABSENT",
    "VISUAL_PROOF_ABSENT",
    "ROWS084_085_086_ACCEPTANCE_ABSENT"
  ],
  "builds_on": {
    "existing_cli": "--verify-synthetic-benchmark-ledger",
    "foundation_commits": [
      "0d5b8087"
    ],
    "foundation_evidence": "Plan/Instructions/QA/Evidence/Wave64/TRK-W64-087_CALIBRATED_TRAJECTORY_FIXTURE_PACKET_CURRENT_DELTA_20260720.json",
    "tip_sha_chain": false
  },
  "checks": [
    {
      "check_id": "ROW087-G01",
      "name": "ci_fixture_ledger_gate_rejects_checked_in_divergence",
      "status": "PASS"
    },
    {
      "check_id": "ROW087-G02",
      "name": "ci_gate_cli_exits_zero_on_checked_in_match",
      "status": "PASS"
    },
    {
      "check_id": "ROW087-G03",
      "name": "verify_synthetic_benchmark_ledger_still_pass",
      "status": "PASS"
    },
    {
      "check_id": "ROW087-009",
      "name": "dependency_row084_complete",
      "status": "FAIL"
    },
    {
      "check_id": "ROW087-010",
      "name": "dependency_row085_complete",
      "status": "FAIL"
    },
    {
      "check_id": "ROW087-011",
      "name": "dependency_row086_complete",
      "status": "FAIL"
    },
    {
      "check_id": "ROW087-014",
      "name": "calibrated_trajectory_benchmark_pass",
      "status": "FAIL"
    },
    {
      "check_id": "ROW087-015",
      "name": "combined_flow_track_contact_audio_visual_review_present",
      "status": "FAIL"
    },
    {
      "check_id": "ROW087-016",
      "name": "direct_row087_runtime_receipt_present",
      "status": "FAIL"
    }
  ],
  "classification": "ROW087_CURRENT_DELTA_CI_FIXTURE_LEDGER_GATE_SLICE_NO_FALSE_COMPLETION",
  "compiler_slice": {
    "ci_fixture_ledger_gate": {
      "checks_checked_in_ledger_matches_rebuild": true,
      "cli_flag": "--ci-gate",
      "function": "run_ci_fixture_ledger_gate",
      "gate_id": "row087_ci_fixture_ledger_gate",
      "production_benchmark": false,
      "rejects_calibrated_trajectory_benchmark_pass_claim": true,
      "rejects_checked_in_divergence": true,
      "rejects_rows084_085_086_acceptance_claim": true,
      "rejects_visual_review_claim": true,
      "row_complete": false,
      "runs_expectation_verifier": true
    },
    "compiler_bytes": 55640,
    "compiler_path": "Plan\\07_IMPLEMENTATION\\scripts\\compile_wave64_motion_force_cues.py",
    "compiler_sha256": "703a98f72e763a0119ac6a3a3f760abd7551f84ff47447f54ebccacd7077270e",
    "decision": "USEFUL_CI_FIXTURE_LEDGER_GATE_SLICE_NOT_PRODUCTION_MOTION_FORCE_AUTHORITY",
    "fail_closed_invariants": [
      "CI/fixture ledger gate fails closed when checked-in ledger digests diverge from fixture-packet rebuild",
      "gate runs ledger-vs-compiled-manifest expectation verifier and rejects digest drift",
      "row_complete and calibrated_trajectory_benchmark_pass remain false",
      "no COMPLETE status mutation; Tracker/Items CSV untouched; Row075 untouched"
    ],
    "fixture_dir": "Plan\\Instructions\\QA\\Evidence\\Wave64\\fixtures\\row087",
    "ledger_expectation_verifier": {
      "cli_flag": "--verify-synthetic-benchmark-ledger",
      "function": "verify_synthetic_ledger_vs_compiled_manifest_expectations",
      "rejects_compiled_manifest_digest_drift": true,
      "rejects_fixture_file_digest_drift": true
    },
    "test_bytes": 23700,
    "test_path": "Plan\\Instructions\\QA\\Scripts\\test_row087_motion_force_cues_compiler.py",
    "test_sha256": "1aa94b63e1b4d8d739be0f57ca20dba3afd733b8b7178b9c0eb3179f1e260432"
  },
  "created_at": "2026-07-20T06:14:30Z",
  "dependency_audit": {
    "notes": [
      "CI/fixture ledger gating does not satisfy upstream Rows084-086 production authority.",
      "Disjoint from Lane D (085/086) mutators; this increment only touches Row087 gate scripts/tests/evidence."
    ],
    "row084_complete": false,
    "row085_complete": false,
    "row086_complete": false
  },
  "evidence_id": "TRK-W64-087_CI_FIXTURE_LEDGER_GATE_CURRENT_DELTA_20260720",
  "focused_local_test_result": {
    "cli_ci_gate_command": "python Plan/07_IMPLEMENTATION/scripts/compile_wave64_motion_force_cues.py --ci-gate",
    "cli_ci_gate_receipt": {
      "authority_ceiling": "fixture_synthetic_only",
      "calibrated_trajectory_benchmark_pass": false,
      "checked_in_matches_rebuild": true,
      "digest_drift_rejected": true,
      "expectation_verifier": "verify_synthetic_ledger_vs_compiled_manifest_expectations",
      "fixture_binding_count": 4,
      "gate": "row087_ci_fixture_ledger_gate",
      "ledger_sha256": "cf13b7fbd445a214bb7d14faf8765e11cf53db1b5d82da9077748960c4c2ea86",
      "production_benchmark": false,
      "row_complete": false,
      "rows084_085_086_acceptance_claimed": false,
      "status": "ok",
      "trajectory_metric_expectation_count": 4,
      "verifier": "run_ci_fixture_ledger_gate",
      "visual_review_claimed": false
    },
    "cli_verify_command": "python Plan/07_IMPLEMENTATION/scripts/compile_wave64_motion_force_cues.py --verify-synthetic-benchmark-ledger",
    "scope_interpretation": "Focused tests prove the fail-closed CI/fixture ledger gate that rejects checked-in ledger divergence from fixture-packet rebuild and runs the ledger-vs-compiled-manifest expectation verifier. They do not grant Row087 completion, calibrated production benchmark pass, Rows084-086 acceptance, runtime receipt, or combined visual review.",
    "strict_command": "python -m pytest -q Plan/Instructions/QA/Scripts/test_row087_motion_force_cues_compiler.py -ra",
    "strict_exit_code": 0,
    "strict_result": "13 passed in 18.61s"
  },
  "highest_proof_tier_achieved": "CONTRACT_FIXTURE_CI_GATE",
  "hold_decision": {
    "decision": "HOLD_ROW087_NO_FALSE_COMPLETION",
    "reason": "Row087 now has a CI/fixture ledger gate (--ci-gate) that fails closed when the checked-in synthetic ledger diverges from a live rebuild of fixture-packet digests, then runs the ledger-vs-compiled-manifest expectation verifier. Thirteen focused tests pass. Rows084-086 remain incomplete. Production optical-flow extraction, calibrated production benchmark pass, runtime receipts, combined visual review, and the tracker-declared output artifact remain absent. The compiler and gate never set row_complete or calibrated_trajectory_benchmark_pass true.",
    "safe_next_action": "Keep Row087 on hold. Upstream continue Rows084/085/086 on disjoint lanes. Do not claim COMPLETE or mutate Tracker/Items CSV from this CI-gate slice."
  },
  "implementation_completion_claimed": false,
  "intent": {
    "allowed_paths": [
      "Plan/07_IMPLEMENTATION/scripts/compile_wave64_motion_force_cues.py",
      "Plan/Instructions/QA/Scripts/test_row087_motion_force_cues_compiler.py",
      "Plan/Instructions/QA/Evidence/Wave64/TRK-W64-087_CI_FIXTURE_LEDGER_GATE_CURRENT_DELTA_20260720.json"
    ],
    "authority_class": "interactive_cursor_integration",
    "classification": "INTERACTIVE_CURSOR_SHIFT_AUTHORITY",
    "dispatch_wake_count": 0,
    "intent_id": "interactive_cursor_shift_row087_ci_fixture_ledger_gate_20260720",
    "routing": null,
    "work_type": "final_authority"
  },
  "item_id": "ITEM-W64-087",
  "ledger_status": "Blocked_Dependencies_Runtime_Benchmark_And_Visual_Proof_Absent_CI_Fixture_Ledger_Gate_Present",
  "ledger_vocabulary_sync": {
    "ledger_status": "Blocked_Dependencies_Runtime_Benchmark_And_Visual_Proof_Absent_CI_Fixture_Ledger_Gate_Present",
    "note": "Triple-synced Tracker/Item from 25cb2f7a; no COMPLETE.",
    "product_completion": false,
    "prove_commits": [
      "25cb2f7a"
    ],
    "runtime_completion": false,
    "synced_at": "2026-07-20T06:20:09.943506Z"
  },
  "library_authority": false,
  "preservation_boundary": {
    "actual_write_paths": [
      "Plan/07_IMPLEMENTATION/scripts/compile_wave64_motion_force_cues.py",
      "Plan/Instructions/QA/Scripts/test_row087_motion_force_cues_compiler.py",
      "Plan/Instructions/QA/Evidence/Wave64/TRK-W64-087_CI_FIXTURE_LEDGER_GATE_CURRENT_DELTA_20260720.json"
    ],
    "unrelated_dirty_paths_preserved": true
  },
  "proof_tier": "CONTRACT_FIXTURE_CI_GATE",
  "proof_tier_detail": {
    "claims": [
      "checked-in synthetic ledger matches live fixture-packet rebuild",
      "ledger\u2194fixture digest drift fail-closed",
      "CI --ci-gate wrapper"
    ],
    "non_claims": [
      "production calibrated trajectory benchmark pass",
      "visual review",
      "Rows084-086 acceptance",
      "row_complete",
      "COMPLETE"
    ],
    "tier": "CONTRACT_FIXTURE_CI_GATE"
  },
  "qa_decision": "HOLD",
  "row_complete": false,
  "runtime_completion_claimed": false,
  "schema_version": "1.0",
  "sibling_lane_disjointness": {
    "disjoint_from_lane_d_084_085_086": true,
    "excluded_sibling_rows": [
      "TRK-W64-075",
      "TRK-W64-084",
      "TRK-W64-085",
      "TRK-W64-086",
      "TRK-W64-088"
    ],
    "row075_paths_touched": false,
    "shared_csv_writes": false
  },
  "status": "HOLD_DEPENDENCIES_RUNTIME_BENCHMARK_AND_VISUAL_PROOF_ABSENT_WITH_CI_FIXTURE_LEDGER_GATE_PRESENT",
  "test_and_runtime_boundary": {
    "ci_fixture_ledger_gate_executed": true,
    "direct_row087_calibration_benchmark_executed": false,
    "direct_row087_visual_review_executed": false,
    "docker_invoked": false,
    "ec2_invoked": false,
    "focused_compiler_tests_executed": true,
    "ledger_expectation_verifier_executed": true,
    "production_row087_extraction_invoked": false,
    "provider_calls": 0,
    "scheduled_task_wakes": 0,
    "wrapper_calls": 0,
    "wsl_invoked": false
  },
  "tracker_id": "TRK-W64-087",
  "updated_at": "2026-07-20T06:20:09.943506Z"
}
